pyvxclient/__init__.py
pyvxclient/client.py
pyvxclient/common.py
pyvxclient/decorators.py
pyvxclient/errors.py
pyvxclient/resource.py
pyvxclient/resources/__init__.py
pyvxclient/resources/api.py
pyvxclient/resources/apiuserpassword.py
pyvxclient/resources/foo.py
pyvxclient/resources/objectaddress.py
pyvxclient/resources/objectinfo.py
pyvxclient/resources/objectmap.py
pyvxclient/resources/order.py
pyvxclient/resources/place.py
pyvxclient/resources/service.py
tests/__init__.py
tests/test_customers.py
tests/data/__init__.py
tests/data/customers.py
tests/data/spec.py
pyvxclient-0.1.3.dist-info/METADATA
pyvxclient-0.1.3.dist-info/WHEEL
pyvxclient-0.1.3.dist-info/top_level.txt
pyvxclient-0.1.3.dist-info/RECORD
